{"notes": [{"time_ms": 0, "lane": "SPACE", "length_ms": 0, "strength": 1.0}, {"time_ms": 492, "lane": "UP", "length_ms": 0, "strength": 0.9}, {"time_ms": 984, "lane": "F", "length_ms": 0, "strength": 1.0}, {"time_ms": 1475, "lane": "RIGHT", "length_ms": 0, "strength": 0.9}, {"time_ms": 1721, "lane": "LEFT", "length_ms": 0, "strength": 0.9}, {"time_ms": 1967, "lane": "SPACE", "length_ms": 0, "strength": 1.0}, {"time_ms": 2951, "lane": "A", "length_ms": 0, "strength": 1.0}, {"time_ms": 3934, "lane": "SPACE", "length_ms": 0, "strength": 1.0}, {"time_ms": 3934, "lane": "DOWN", "length_ms": 0, "strength": 0.9}, {"time_ms": 4426, "lane": "UP", "length_ms": 0, "strength": 0.9}, {"time_ms": 4918, "lane": "S", "length_ms": 0, "strength": 1.0}, {"time_ms": 5902, "lane": "SPACE", "length_ms": 0, "strength": 1.0}, {"time_ms": 5902, "lane": "RIGHT", "length_ms": 0, "strength": 0.9}, {"time_ms": 5902, "lane": "D", "length_ms": 0, "strength": 1.0}, {"time_ms": 7377, "lane": "LEFT", "length_ms": 0, "strength": 0.9}, {"time_ms": 7869, "lane": "SPACE", "length_ms": 0, "strength": 1.0}, {"time_ms": 7869, "lane": "DOWN", "length_ms": 0, "strength": 0.9}, {"time_ms": 7869, "lane": "F", "length_ms": 0, "strength": 1.0}, {"time_ms": 8852, "lane": "UP", "length_ms": 0, "strength": 0.9}, {"time_ms": 8852, "lane": "A", "length_ms": 0, "strength": 1.0}, {"time_ms": 9344, "lane": "RIGHT", "length_ms": 0, "strength": 0.9}, {"time_ms": 9836, "lane": "SPACE", "length_ms": 0, "strength": 1.0}, {"time_ms": 9836, "lane": "S", "length_ms": 0, "strength": 1.0}, {"time_ms": 10328, "lane": "LEFT", "length_ms": 0, "strength": 0.9}, {"time_ms": 10820, "lane": "DOWN", "length_ms": 0, "strength": 0.9}, {"time_ms": 11803, "lane": "SPACE", "length_ms": 0, "strength": 1.0}, {"time_ms": 11803, "lane": "UP", "length_ms": 0, "strength": 0.9}, {"time_ms": 12049, "lane": "RIGHT", "length_ms": 0, "strength": 0.9}, {"time_ms": 12295, "lane": "LEFT", "length_ms": 0, "strength": 0.9}, {"time_ms": 12787, "lane": "D", "length_ms": 0, "strength": 1.0}, {"time_ms": 13770, "lane": "SPACE", "length_ms": 0, "strength": 1.0}, {"time_ms": 14262, "lane": "DOWN", "length_ms": 0, "strength": 0.9}], "loop_ms": 15738, "lanes": ["A", "S", "D", "F", "SPACE", "LEFT", "DOWN", "UP", "RIGHT"], "meta": {"bpm": 122.0, "bars": 8, "timesig": [4, 4], "mood": "brooding", "source_hash": "a62c5e8235c1a287aa36fa9d2ae30b642ef753f2", "title": "Electric Bazaar Reverb"}}